scripts/__init__.py
scripts/transport.py
fiscal_printer_adapter-0.0.3.dist-info/METADATA
fiscal_printer_adapter-0.0.3.dist-info/WHEEL
fiscal_printer_adapter-0.0.3.dist-info/top_level.txt
fiscal_printer_adapter-0.0.3.dist-info/RECORD
